trclip/__init__.py
trclip/cli.py
trclip/trclip.py
trclip/visualizer.py
trclip-0.1.31.dist-info/LICENSE
trclip-0.1.31.dist-info/METADATA
trclip-0.1.31.dist-info/WHEEL
trclip-0.1.31.dist-info/entry_points.txt
trclip-0.1.31.dist-info/top_level.txt
trclip-0.1.31.dist-info/RECORD
