Metadata-Version: 2.1
Name: trclip
Version: 0.1.31
Summary: A Turkish CLIP
Home-page: https://github.com/yusufani/trclip
Author: Yusuf ANI
Author-email: yusufani8@gmail.com
License: MIT license
Keywords: trclip
Classifier: Development Status :: 2 - Pre-Alpha
Classifier: Intended Audience :: Developers
Classifier: License :: OSI Approved :: MIT License
Classifier: Natural Language :: English
Classifier: Programming Language :: Python :: 3
Classifier: Programming Language :: Python :: 3.6
Classifier: Programming Language :: Python :: 3.7
Classifier: Programming Language :: Python :: 3.8
Requires-Python: >=3.6
License-File: LICENSE
Requires-Dist: Click (>=7.0)
